instapi/__init__.py
instapi/cache.py
instapi/client.py
instapi/client_api/__init__.py
instapi/client_api/base.py
instapi/client_api/client.py
instapi/client_api/direct.py
instapi/exceptions.py
instapi/models/__init__.py
instapi/models/base.py
instapi/models/comment.py
instapi/models/direct.py
instapi/models/feed.py
instapi/models/media.py
instapi/models/resource.py
instapi/models/story.py
instapi/models/user.py
instapi/types.py
instapi/utils.py
inst_api-0.3.0.dist-info/LICENSE
inst_api-0.3.0.dist-info/WHEEL
inst_api-0.3.0.dist-info/METADATA
inst_api-0.3.0.dist-info/RECORD
