Metadata-Version: 2.1
Name: inst-api
Version: 0.3.0
Summary: InstAPI - comfortable and easy to use Python's library for interaction with Instagram
Home-page: https://github.com/uriyyo/instapi
License: MIT
Author: Yurii Karabas
Author-email: 1998uriyyo@gmail.com
Requires-Python: >=3.7,<4.0
Classifier: License :: OSI Approved :: MIT License
Classifier: Operating System :: OS Independent
Classifier: Programming Language :: Python
Classifier: Programming Language :: Python :: 3
Classifier: Programming Language :: Python :: 3 :: Only
Classifier: Programming Language :: Python :: 3.7
Classifier: Programming Language :: Python :: 3.8
Classifier: Programming Language :: Python :: 3.9
Provides-Extra: pillow
Requires-Dist: instagram-private-api (>=1.6.0,<2.0.0)
Requires-Dist: pillow (>=7.2.0); extra == "pillow"
Requires-Dist: requests (>=2.24.0)
Project-URL: Repository, https://github.com/uriyyo/instapi
